MCX.v
module MCX(
    input clk, rst);
    
    //Program Counter [4b] Conditional[2 bits] Instruction[4 bits] arg1[12 bits] arg2[12 bits] arg3 [12 bits]
    reg [3:0] PC;
    reg [1:0] cond;
    reg [3:0] inst;
    reg signed [10:0] args [2:0];
    
    //registers
    reg signed [10:0] acc;


    reg [3:0] next_inst;

    wire [45:0] line;

    wire signed [10:0] alu_out;

    parameter acc_addr = 1;

    alu ALU1(.inst(inst), .arg1(args[0]), .arg2(args[1]), .acc(acc), .out(alu_out)); 
    prog_mem MEM(.rst(rst), .addr(next_inst), .line(line));

    //Load next instruction
    always @(posedge clk) begin
        PC <= line[45:42];
        cond <= line[41:40];
        inst <= line[39:36];
        args[0] <= line[35:24];
        args[1] <= line[23:12];
        args[2] <= line[11:0];
    end

    //Queue next instruction to be loaded
    always @(*) begin
            if(inst == 4'h3)
                next_inst <= args[0];
            else if(PC == 6)
                next_inst <= 0;
            else
                next_inst <= PC + 1;
    end

    //Update acc register
    always @(posedge clk) begin
        if(inst != 4'h1) acc <= alu_out;
        else if(args[2] == acc_addr) acc <= args[1];
        else acc <= acc;
    end


    //Reset
    always @(*) begin
        if(!rst) begin
            acc <= 0;
            PC <= 15;
            inst <= 0;
        end
    end
endmodule

module prog_mem(
    input rst,
    input [3:0] addr,
    output reg [45:0] line);

    reg [41:0] mem [6:0];

    always @(*) begin
        line <= {addr,mem[addr]};
    end

    always @(*) begin
        if(!rst) begin
            mem[0] = {2'h0,4'h5,12'd1,12'b0,12'b0}; //Add 1
            mem[1] = {2'h0,4'h5,12'd2,12'b0,12'b0}; //Add 2
            mem[2] = {2'h0,4'h5,12'd3,12'b0,12'b0}; //Add 3
            mem[3] = {2'h0,4'h5,12'd4,12'b0,12'b0}; //Add 4
            mem[4] = {2'h0,4'h5,12'd5,12'b0,12'b0}; //Add 5
            mem[5] = {2'h0,4'h5,12'd6,12'b0,12'b0}; //Add 6
            mem[6] = {2'h0,4'h5,12'd7,12'b0,12'b0}; //Add 7
        end
    end
endmodule

alu/notop.v
module notop(
  input signed [10:0] acc,
  output reg signed [10:0] out);
  
  always @(*)
  begin
    if(acc == 0)
      out <= 100;
    else
      out <= 0;
  end
endmodule

alu/mul.v
module mul(acc, arg1, out);
  input signed [10:0] acc;
  input signed [10:0] arg1;

  output reg signed [10:0] out;

  wire signed [21:0] tmp;
  
  assign tmp = acc * arg1;
  always @(*) begin
    if(tmp > 999) out = 999;
    else if(tmp < -999) out = -999;
    else  out = tmp[10:0];
  end
endmodule

alu/sub.v
module sub(
  input signed [10:0] arg1, acc,
  output reg [10:0] out);

  wire signed [11:0] tmp;

  assign tmp = acc-arg1;

  always @(*) begin //overflow handler
    if(tmp>999) out <= 999;
    else if(tmp<-999) out <= -999;
    else out<=tmp;
  end
endmodule

alu/add.v
module add(arg1, acc, out);
  input signed [10:0] arg1;
  input signed [10:0] acc;
  
  output reg [10:0] out;

  wire signed [11:0] tmp;

  assign tmp = acc+arg1;

  always @(*) begin //Overflow handler
    if(tmp>999) out <= 999;
    else if(tmp<-999) out <= -999;
    else out<=tmp;
  end
endmodule

alu/alu.v
/*`include "add.v"
`include "sub.v"
`include "notop.v"
`include "mul.v"
*/

module alu(
  input wire [3:0] inst,
  input wire [10:0] arg1, arg2, acc,
  output reg [10:0] out);
  
  wire signed [10:0] add_out, sub_out, mul_out, not_out;
  //signed reg dgt_out;
  //signed reg dst_out;

  add UADD(.arg1(arg1), .acc(acc), .out(add_out));
  sub USUB(.arg1(arg1), .acc(acc), .out(sub_out));
  mul UMUL(.arg1(arg1), .acc(acc), .out(mul_out));
  notop UNOT(.acc(acc), .out(not_out));
  //dgt UDGT(.arg1(arg1), .acc(acc), .out(dgt_out);
  //dst UDST(.arg1(arg1),.arg2(arg2),.acc(acc),.out(dst_out))

  always @(*) begin
    case(inst)
      5 : out <= add_out;
      6 : out <= sub_out;
      7 : out <= mul_out;
      8 : out <= not_out;
      //10 : acc <= dgt_out;
      //11 : acc <= dst_out;
      default: out <= acc;
    endcase
  end
endmodule

tests/MCX_tb.v
module MCX_tb();

  reg signed [10:0] arg1;
  reg signed [10:0] arg2;
  reg signed [10:0] arg3;
  reg signed [3:0] inst;
  reg clk;
  reg rst;

  MCX DOT (.clk(clk), .rst(rst));

  initial
  begin
    $display("Resting at initial conditions.");
    clk = 0;
    rst = 0;
    #1;
    rst = 1;
    #10;
    #100;
    $display("Stopping");
    $stop;
  end

  initial begin
    $dumpfile("MCX_tb_dump.vcd");
    $dumpvars(0,DOT);
  end

  always
    #5 clk = !clk;
endmodule

MCX_tb_dump.vcd
$date
	Wed Jun 10 18:44:57 2020
$end
$version
	Icarus Verilog
$end
$timescale
	1s
$end
$scope module MCX_tb $end
$scope module DOT $end
$var wire 1 ! clk $end
$var wire 1 " rst $end
$var wire 46 # line [45:0] $end
$var wire 11 $ alu_out [10:0] $end
$var reg 4 % PC [3:0] $end
$var reg 11 & acc [10:0] $end
$var reg 2 ' cond [1:0] $end
$var reg 4 ( inst [3:0] $end
$var reg 4 ) next_inst [3:0] $end
$scope module ALU1 $end
$var wire 11 * acc [10:0] $end
$var wire 11 + arg1 [10:0] $end
$var wire 11 , arg2 [10:0] $end
$var wire 4 - inst [3:0] $end
$var wire 11 . sub_out [10:0] $end
$var wire 11 / not_out [10:0] $end
$var wire 11 0 mul_out [10:0] $end
$var wire 11 1 add_out [10:0] $end
$var reg 11 2 out [10:0] $end
$scope module UADD $end
$var wire 11 3 acc [10:0] $end
$var wire 11 4 arg1 [10:0] $end
$var wire 12 5 tmp [11:0] $end
$var reg 11 6 out [10:0] $end
$upscope $end
$scope module UMUL $end
$var wire 11 7 acc [10:0] $end
$var wire 11 8 arg1 [10:0] $end
$var wire 22 9 tmp [21:0] $end
$var reg 11 : out [10:0] $end
$upscope $end
$scope module UNOT $end
$var wire 11 ; acc [10:0] $end
$var reg 11 < out [10:0] $end
$upscope $end
$scope module USUB $end
$var wire 11 = acc [10:0] $end
$var wire 11 > arg1 [10:0] $end
$var wire 12 ? tmp [11:0] $end
$var reg 11 @ out [10:0] $end
$upscope $end
$upscope $end
$scope module MEM $end
$var wire 4 A addr [3:0] $end
$var wire 1 " rst $end
$var reg 46 B line [45:0] $end
$upscope $end
$upscope $end
$upscope $end
$enddefinitions $end
#0
$dumpvars
b101000000000001000000000000000000000000 B
b0 A
bx @
bx ?
bx >
b0 =
b1100100 <
b0 ;
bx :
bx 9
bx 8
b0 7
bx 6
bx 5
bx 4
b0 3
b0 2
bx 1
bx 0
b1100100 /
bx .
b0 -
bx ,
bx +
b0 *
b0 )
b0 (
bx '
b0 &
b1111 %
b0 $
b101000000000001000000000000000000000000 #
0"
0!
$end
#1
1"
#5
b1000101000000000010000000000000000000000000 #
b1000101000000000010000000000000000000000000 B
b1 1
b1 6
b0 0
b0 :
b11111111111 .
b11111111111 @
b1 $
b1 2
b1 )
b1 A
b0 ,
b1 5
b0 9
b111111111111 ?
b1 +
b1 4
b1 8
b1 >
b101 (
b101 -
b0 '
b0 %
1!
#10
0!
#15
b11 $
b11 2
b10000101000000000011000000000000000000000000 #
b10000101000000000011000000000000000000000000 B
b10 0
b10 :
b0 /
b0 <
b11 1
b11 6
b10 )
b10 A
b10 9
b1 &
b1 *
b1 3
b1 7
b1 ;
b1 =
b11 5
b111111111111 ?
b10 +
b10 4
b10 8
b10 >
b1 %
1!
#20
0!
#25
b11000101000000000100000000000000000000000000 #
b11000101000000000100000000000000000000000000 B
b110 $
b110 2
b11 )
b11 A
b110 1
b110 6
b1001 0
b1001 :
b0 .
b0 @
b11 +
b11 4
b11 8
b11 >
b10 %
b110 5
b1001 9
b0 ?
b11 &
b11 *
b11 3
b11 7
b11 ;
b11 =
1!
#30
0!
#35
b1010 $
b1010 2
b100000101000000000101000000000000000000000000 #
b100000101000000000101000000000000000000000000 B
b1010 1
b1010 6
b11000 0
b11000 :
b10 .
b10 @
b100 )
b100 A
b110 &
b110 *
b110 3
b110 7
b110 ;
b110 =
b1010 5
b11000 9
b10 ?
b100 +
b100 4
b100 8
b100 >
b11 %
1!
#40
0!
#45
b101000101000000000110000000000000000000000000 #
b101000101000000000110000000000000000000000000 B
b1111 $
b1111 2
b101 )
b101 A
b1111 1
b1111 6
b110010 0
b110010 :
b101 .
b101 @
b101 +
b101 4
b101 8
b101 >
b100 %
b1111 5
b110010 9
b101 ?
b1010 &
b1010 *
b1010 3
b1010 7
b1010 ;
b1010 =
1!
#50
0!
#55
b10101 $
b10101 2
b110000101000000000111000000000000000000000000 #
b110000101000000000111000000000000000000000000 B
b10101 1
b10101 6
b1011010 0
b1011010 :
b1001 .
b1001 @
b110 )
b110 A
b1111 &
b1111 *
b1111 3
b1111 7
b1111 ;
b1111 =
b10101 5
b1011010 9
b1001 ?
b110 +
b110 4
b110 8
b110 >
b101 %
1!
#60
0!
#65
b101000000000001000000000000000000000000 #
b101000000000001000000000000000000000000 B
b11100 $
b11100 2
b0 )
b0 A
b11100 1
b11100 6
b10010011 0
b10010011 :
b1110 .
b1110 @
b111 +
b111 4
b111 8
b111 >
b110 %
b11100 5
b10010011 9
b1110 ?
b10101 &
b10101 *
b10101 3
b10101 7
b10101 ;
b10101 =
1!
#70
0!
#75
b11101 $
b11101 2
b1000101000000000010000000000000000000000000 #
b1000101000000000010000000000000000000000000 B
b11101 1
b11101 6
b11100 0
b11100 :
b11011 .
b11011 @
b1 )
b1 A
b11100 &
b11100 *
b11100 3
b11100 7
b11100 ;
b11100 =
b11101 5
b11100 9
b11011 ?
b1 +
b1 4
b1 8
b1 >
b0 %
1!
#80
0!
#85
b10000101000000000011000000000000000000000000 #
b10000101000000000011000000000000000000000000 B
b11111 $
b11111 2
b10 )
b10 A
b11111 1
b11111 6
b111010 0
b111010 :
b10 +
b10 4
b10 8
b10 >
b1 %
b11111 5
b111010 9
b11011 ?
b11101 &
b11101 *
b11101 3
b11101 7
b11101 ;
b11101 =
1!
#90
0!
#95
b100010 $
b100010 2
b11000101000000000100000000000000000000000000 #
b11000101000000000100000000000000000000000000 B
b100010 1
b100010 6
b1011101 0
b1011101 :
b11100 .
b11100 @
b11 )
b11 A
b11111 &
b11111 *
b11111 3
b11111 7
b11111 ;
b11111 =
b100010 5
b1011101 9
b11100 ?
b11 +
b11 4
b11 8
b11 >
b10 %
1!
#100
0!
#105
b100000101000000000101000000000000000000000000 #
b100000101000000000101000000000000000000000000 B
b100110 $
b100110 2
b100 )
b100 A
b100110 1
b100110 6
b10001000 0
b10001000 :
b11110 .
b11110 @
b100 +
b100 4
b100 8
b100 >
b11 %
b100110 5
b10001000 9
b11110 ?
b100010 &
b100010 *
b100010 3
b100010 7
b100010 ;
b100010 =
1!
